ezmsg/zmq/__init__.py
ezmsg/zmq/__version__.py
ezmsg/zmq/pubsub.py
ezmsg/zmq/repreq.py
ezmsg/zmq/units.py
ezmsg/zmq/util.py
ezmsg_zmq-1.4.3.dist-info/METADATA
ezmsg_zmq-1.4.3.dist-info/WHEEL
ezmsg_zmq-1.4.3.dist-info/licenses/LICENSE
ezmsg_zmq-1.4.3.dist-info/RECORD
