Metadata-Version: 2.4
Name: ezmsg-zmq
Version: 1.4.3
Summary: Zero-MQ pub/sub units for ezmsg
Author-email: Griffin Milsap <griffin.milsap@gmail.com>, Preston Peranich <pperanich@gmail.com>, Chadwick Boulay <chadwick.boulay@gmail.com>
License-Expression: MIT
License-File: LICENSE
Requires-Python: >=3.10.15
Requires-Dist: ezmsg>=3.6.0
Requires-Dist: pyzmq>=25.1.2
Requires-Dist: tornado>=6.4.2; platform_system == 'Windows'
